seed_salesforce/__init__.py
seed_salesforce/salesforce_client.py
seed_salesforce-0.1.1.dist-info/LICENSE.md
seed_salesforce-0.1.1.dist-info/WHEEL
seed_salesforce-0.1.1.dist-info/METADATA
seed_salesforce-0.1.1.dist-info/RECORD
