Metadata-Version: 2.1
Name: seed-salesforce
Version: 0.1.1
Summary: Package for connecting SEED data to Salesforce
Home-page: https://seed-platform.org
License: BSD-3-Clause
Keywords: SEED Platform,Building Benchmarking,Salesforce,Building Performance Standard
Author: Nicholas Long
Author-email: nicholas.long@nrel.gov
Requires-Python: >=3.9,<3.13
Classifier: Development Status :: 4 - Beta
Classifier: Intended Audience :: Developers
Classifier: License :: OSI Approved :: BSD License
Classifier: Programming Language :: Python :: 3
Classifier: Programming Language :: Python :: 3.9
Classifier: Programming Language :: Python :: 3.10
Classifier: Programming Language :: Python :: 3.11
Classifier: Programming Language :: Python :: 3.10
Classifier: Programming Language :: Python :: 3.11
Classifier: Programming Language :: Python :: 3.12
Classifier: Programming Language :: Python :: 3.9
Requires-Dist: python-dateutil
Requires-Dist: simple-salesforce (>=1.12.6,<2.0.0)
Project-URL: Documentation, https://seed-platform.org
Project-URL: Repository, https://github.com/seed-platform/seed-salesforce
